vibhu4agarwal/__init__.py
vibhu4agarwal/details.py
vibhu4agarwal/prints.py
vibhu4agarwal/vibhu.py
vibhu4agarwal-1.1.0.dist-info/LICENSE
vibhu4agarwal-1.1.0.dist-info/METADATA
vibhu4agarwal-1.1.0.dist-info/WHEEL
vibhu4agarwal-1.1.0.dist-info/entry_points.txt
vibhu4agarwal-1.1.0.dist-info/top_level.txt
vibhu4agarwal-1.1.0.dist-info/RECORD
