Metadata-Version: 2.1
Name: vibhu4agarwal
Version: 1.1.0
Summary: Interactive Resume of Vibhu Agarwal.
Home-page: https://github.com/Vibhu-Agarwal/vibhu4agarwal
Author: Vibhu Agarwal
Author-email: vibhu4agarwal@gmail.com
License: GPLv3+
Keywords: resume portfolio vibhu4agarwal
Platform: UNKNOWN
Classifier: Programming Language :: Python :: 3
Classifier: License :: OSI Approved :: GNU General Public License v3 or later (GPLv3+)
Classifier: Operating System :: OS Independent
